pywiki
